{"v":"5.9.0","fr":29.9700012207031,"ip":0,"op":58.0000023623884,"w":292,"h":270,"nm":"export","ddd":0,"assets":[{"id":"comp_0","nm":"Final_11","fr":25,"layers":[{"ddd":0,"ind":1,"ty":0,"nm":"Pre-comp 4","refId":"comp_1","sr":-1,"ks":{"o":{"a":0,"k":100,"ix":11},"r":{"a":0,"k":0,"ix":10},"p":{"a":0,"k":[960,540,0],"ix":2,"l":2},"a":{"a":0,"k":[960,540,0],"ix":1,"l":2},"s":{"a":0,"k":[100,100,100],"ix":6,"l":2}},"ao":0,"w":1920,"h":1080,"ip":122.267614980062,"op":61.1388024902344,"st":122.277604980469,"bm":0},{"ddd":0,"ind":2,"ty":0,"nm":"Pre-comp 4","refId":"comp_1","sr":1,"ks":{"o":{"a":0,"k":100,"ix":11},"r":{"a":0,"k":0,"ix":10},"p":{"a":0,"k":[960,540,0],"ix":2,"l":2},"a":{"a":0,"k":[960,540,0],"ix":1,"l":2},"s":{"a":0,"k":[100,100,100],"ix":6,"l":2}},"ao":0,"w":1920,"h":1080,"ip":0,"op":61.1388024902344,"st":0,"bm":0},{"ddd":0,"ind":7,"ty":0,"nm":"Pre-comp 3","refId":"comp_3","sr":1,"ks":{"o":{"a":0,"k":100,"ix":11},"r":{"a":0,"k":0,"ix":10},"p":{"a":0,"k":[960,522,0],"ix":2,"l":2},"a":{"a":0,"k":[960,540,0],"ix":1,"l":2},"s":{"a":0,"k":[59,59,100],"ix":6,"l":2}},"ao":0,"tm":{"a":1,"k":[{"i":{"x":[0.833],"y":[0.833]},"o":{"x":[0.167],"y":[0.167]},"t":0,"s":[0]},{"i":{"x":[0.833],"y":[0.833]},"o":{"x":[0.167],"y":[0.167]},"t":329.67,"s":[14.56]},{"t":449.550018310547,"s":[15]}],"ix":2},"w":1920,"h":1080,"ip":0,"op":436.363217773437,"st":0,"bm":0}]},{"id":"comp_1","nm":"Pre-comp 4","fr":25,"layers":[{"ddd":0,"ind":1,"ty":5,"nm":"loading LUX visualizer... 2","sr":1,"ks":{"o":{"a":1,"k":[{"i":{"x":[0.833],"y":[0.833]},"o":{"x":[0.167],"y":[0.167]},"t":4.795,"s":[0]},{"t":28.9795863366127,"s":[100]}],"ix":11},"r":{"a":0,"k":0,"ix":10},"p":{"s":true,"x":{"a":0,"k":962.198,"ix":3},"y":{"a":1,"k":[{"i":{"x":[0.18],"y":[1]},"o":{"x":[0.013],"y":[0.12]},"t":4.795,"s":[481.247]},{"t":29.0580234491825,"s":[580.247]}],"ix":4}},"a":{"a":0,"k":[0,0,0],"ix":1,"l":2},"s":{"a":1,"k":[{"i":{"x":[0.355,0.355,0.667],"y":[1,1,1]},"o":{"x":[0.024,0.024,0.333],"y":[0.293,0.293,0]},"t":4.795,"s":[8,8,100]},{"t":59.9400024414062,"s":[37,37,100]}],"ix":6,"l":2}},"ao":0,"t":{"d":{"k":[{"s":{"s":65,"f":"FuturaPT-Book","t":"loading LUX visualizer...","ca":0,"j":2,"tr":37,"lh":98,"ls":0,"fc":[1,1,1]},"t":0}]},"p":{},"m":{"g":1,"a":{"a":0,"k":[0,0],"ix":2}},"a":[{"nm":"Animator 1","s":{"t":0,"xe":{"a":0,"k":0,"ix":7},"ne":{"a":0,"k":0,"ix":8},"a":{"a":0,"k":100,"ix":4},"b":1,"rn":0,"sh":1,"sm":{"a":0,"k":100,"ix":6},"s":{"a":1,"k":[{"i":{"x":[0.735],"y":[1]},"o":{"x":[0.32],"y":[0]},"t":19.181,"s":[0]},{"t":58.7412023925781,"s":[100]}],"ix":1},"r":1},"a":{"o":{"a":0,"k":0,"ix":9}}}]},"ip":0,"op":449.550018310547,"st":0,"bm":0},{"ddd":0,"ind":2,"ty":5,"nm":"loading LUX visualizer...","sr":1,"ks":{"o":{"a":1,"k":[{"i":{"x":[0.833],"y":[0.833]},"o":{"x":[0.167],"y":[0.167]},"t":4.795,"s":[0]},{"t":28.771201171875,"s":[50]}],"ix":11},"r":{"a":0,"k":0,"ix":10},"p":{"s":true,"x":{"a":0,"k":962.198,"ix":3},"y":{"a":1,"k":[{"i":{"x":[0.18],"y":[1]},"o":{"x":[0.013],"y":[0.12]},"t":4.795,"s":[481.247]},{"t":29.0580234491825,"s":[580.247]}],"ix":4}},"a":{"a":0,"k":[0,0,0],"ix":1,"l":2},"s":{"a":1,"k":[{"i":{"x":[0.355,0.355,0.667],"y":[1,1,1]},"o":{"x":[0.024,0.024,0.333],"y":[0.293,0.293,0]},"t":4.795,"s":[8,8,100]},{"t":59.9400024414062,"s":[37,37,100]}],"ix":6,"l":2}},"ao":0,"t":{"d":{"k":[{"s":{"s":65,"f":"FuturaPT-Book","t":"loading LUX visualizer...","ca":0,"j":2,"tr":37,"lh":98,"ls":0,"fc":[1,1,1]},"t":0}]},"p":{},"m":{"g":1,"a":{"a":0,"k":[0,0],"ix":2}},"a":[{"nm":"Animator 1","s":{"t":0,"xe":{"a":0,"k":0,"ix":7},"ne":{"a":0,"k":0,"ix":8},"a":{"a":0,"k":100,"ix":4},"b":1,"rn":0,"sh":1,"sm":{"a":0,"k":100,"ix":6},"s":{"a":1,"k":[{"i":{"x":[0.536],"y":[1]},"o":{"x":[0.008],"y":[0.261]},"t":4.795,"s":[0]},{"t":53.1674845874309,"s":[100]}],"ix":1},"r":1},"a":{"o":{"a":0,"k":0,"ix":9}}}]},"ip":0,"op":449.550018310547,"st":0,"bm":0},{"ddd":0,"ind":3,"ty":0,"nm":"line","refId":"comp_2","sr":1,"ks":{"o":{"a":0,"k":100,"ix":11},"r":{"a":0,"k":0,"ix":10},"p":{"a":0,"k":[960,600.286,0],"ix":2,"l":2},"a":{"a":0,"k":[960,540,0],"ix":1,"l":2},"s":{"a":1,"k":[{"i":{"x":[0.386,0.386,0.667],"y":[1,1,1]},"o":{"x":[0.012,0.012,0.333],"y":[0.514,0.514,0]},"t":15.584,"s":[0,0,100]},{"t":64.7352026367188,"s":[45,45,100]}],"ix":6,"l":2}},"ao":0,"w":1920,"h":1080,"ip":0,"op":449.550018310547,"st":0,"bm":0}]},{"id":"comp_2","nm":"line","fr":25,"layers":[{"ddd":0,"ind":1,"ty":4,"nm":"Shape Layer 2","sr":1,"ks":{"o":{"a":0,"k":100,"ix":11},"r":{"a":0,"k":0,"ix":10},"p":{"a":0,"k":[982.714,481.143,0],"ix":2,"l":2},"a":{"a":0,"k":[0,0,0],"ix":1,"l":2},"s":{"a":0,"k":[100,100,100],"ix":6,"l":2}},"ao":0,"ef":[{"ty":21,"nm":"Fill","np":9,"mn":"ADBE Fill","ix":1,"en":1,"ef":[{"ty":10,"nm":"Fill Mask","mn":"ADBE Fill-0001","ix":1,"v":{"a":0,"k":0,"ix":1}},{"ty":7,"nm":"All Masks","mn":"ADBE Fill-0007","ix":2,"v":{"a":0,"k":0,"ix":2}},{"ty":2,"nm":"Color","mn":"ADBE Fill-0002","ix":3,"v":{"a":0,"k":[1,0,0,1],"ix":3}},{"ty":7,"nm":"Invert","mn":"ADBE Fill-0006","ix":4,"v":{"a":0,"k":0,"ix":4}},{"ty":0,"nm":"Horizontal Feather","mn":"ADBE Fill-0003","ix":5,"v":{"a":0,"k":0,"ix":5}},{"ty":0,"nm":"Vertical Feather","mn":"ADBE Fill-0004","ix":6,"v":{"a":0,"k":0,"ix":6}},{"ty":0,"nm":"Opacity","mn":"ADBE Fill-0005","ix":7,"v":{"a":0,"k":1,"ix":7}}]}],"shapes":[{"ty":"gr","it":[{"ind":0,"ty":"sh","ix":1,"ks":{"a":0,"k":{"i":[[0,0],[0,0]],"o":[[0,0],[0,0]],"v":[[-249,68],[219,68]],"c":false},"ix":2},"nm":"Path 1","mn":"ADBE Vector Shape - Group","hd":false},{"ty":"tm","s":{"a":0,"k":0,"ix":1},"e":{"a":1,"k":[{"i":{"x":[0.398],"y":[1]},"o":{"x":[0.034],"y":[0.326]},"t":20.38,"s":[0]},{"t":76.723203125,"s":[100]}],"ix":2},"o":{"a":0,"k":0,"ix":3},"m":1,"ix":2,"nm":"Trim Paths 1","mn":"ADBE Vector Filter - Trim","hd":false},{"ty":"st","c":{"a":0,"k":[1,1,1,1],"ix":3},"o":{"a":0,"k":100,"ix":4},"w":{"a":0,"k":3,"ix":5},"lc":1,"lj":1,"ml":4,"bm":0,"nm":"Stroke 1","mn":"ADBE Vector Graphic - Stroke","hd":false},{"ty":"fl","c":{"a":0,"k":[0.031387927485,0.196366164264,0.61568627451,1],"ix":4},"o":{"a":0,"k":100,"ix":5},"r":1,"bm":0,"nm":"Fill 1","mn":"ADBE Vector Graphic - Fill","hd":false},{"ty":"tr","p":{"a":0,"k":[0,0],"ix":2},"a":{"a":0,"k":[0,0],"ix":1},"s":{"a":0,"k":[100,100],"ix":3},"r":{"a":0,"k":0,"ix":6},"o":{"a":0,"k":100,"ix":7},"sk":{"a":0,"k":0,"ix":4},"sa":{"a":0,"k":0,"ix":5},"nm":"Transform"}],"nm":"Shape 1","np":4,"cix":2,"bm":0,"ix":1,"mn":"ADBE Vector Group","hd":false}],"ip":0,"op":449.550018310547,"st":0,"bm":0},{"ddd":0,"ind":2,"ty":4,"nm":"Shape Layer 1","sr":1,"ks":{"o":{"a":0,"k":100,"ix":11},"r":{"a":0,"k":0,"ix":10},"p":{"a":0,"k":[982.714,481.143,0],"ix":2,"l":2},"a":{"a":0,"k":[0,0,0],"ix":1,"l":2},"s":{"a":0,"k":[100,100,100],"ix":6,"l":2}},"ao":0,"ef":[{"ty":21,"nm":"Fill","np":9,"mn":"ADBE Fill","ix":1,"en":1,"ef":[{"ty":10,"nm":"Fill Mask","mn":"ADBE Fill-0001","ix":1,"v":{"a":0,"k":0,"ix":1}},{"ty":7,"nm":"All Masks","mn":"ADBE Fill-0007","ix":2,"v":{"a":0,"k":0,"ix":2}},{"ty":2,"nm":"Color","mn":"ADBE Fill-0002","ix":3,"v":{"a":0,"k":[0.211764708161,0.211764708161,0.211764708161,1],"ix":3}},{"ty":7,"nm":"Invert","mn":"ADBE Fill-0006","ix":4,"v":{"a":0,"k":0,"ix":4}},{"ty":0,"nm":"Horizontal Feather","mn":"ADBE Fill-0003","ix":5,"v":{"a":0,"k":0,"ix":5}},{"ty":0,"nm":"Vertical Feather","mn":"ADBE Fill-0004","ix":6,"v":{"a":0,"k":0,"ix":6}},{"ty":0,"nm":"Opacity","mn":"ADBE Fill-0005","ix":7,"v":{"a":0,"k":1,"ix":7}}]}],"shapes":[{"ty":"gr","it":[{"ind":0,"ty":"sh","ix":1,"ks":{"a":0,"k":{"i":[[0,0],[0,0]],"o":[[0,0],[0,0]],"v":[[-249,68],[219,68]],"c":false},"ix":2},"nm":"Path 1","mn":"ADBE Vector Shape - Group","hd":false},{"ty":"st","c":{"a":0,"k":[1,0.729411764706,0,1],"ix":3},"o":{"a":0,"k":100,"ix":4},"w":{"a":0,"k":3,"ix":5},"lc":1,"lj":1,"ml":4,"bm":0,"nm":"Stroke 1","mn":"ADBE Vector Graphic - Stroke","hd":false},{"ty":"fl","c":{"a":0,"k":[0.031387927485,0.196366164264,0.61568627451,1],"ix":4},"o":{"a":0,"k":100,"ix":5},"r":1,"bm":0,"nm":"Fill 1","mn":"ADBE Vector Graphic - Fill","hd":false},{"ty":"tr","p":{"a":0,"k":[0,0],"ix":2},"a":{"a":0,"k":[0,0],"ix":1},"s":{"a":0,"k":[100,100],"ix":3},"r":{"a":0,"k":0,"ix":6},"o":{"a":0,"k":100,"ix":7},"sk":{"a":0,"k":0,"ix":4},"sa":{"a":0,"k":0,"ix":5},"nm":"Transform"}],"nm":"Shape 1","np":3,"cix":2,"bm":0,"ix":1,"mn":"ADBE Vector Group","hd":false}],"ip":0,"op":449.550018310547,"st":0,"bm":0}]},{"id":"comp_3","nm":"Pre-comp 3","fr":25,"layers":[{"ddd":0,"ind":1,"ty":0,"nm":"Pre-comp 2","refId":"comp_4","sr":-1,"ks":{"o":{"a":0,"k":100,"ix":11},"r":{"a":1,"k":[{"i":{"x":[0.583],"y":[1]},"o":{"x":[0.024],"y":[1.043]},"t":438.751,"s":[90]},{"t":372.81682518514,"s":[0]}],"ix":10},"p":{"a":0,"k":[966,482.286,0],"ix":2,"l":2},"a":{"a":0,"k":[966,482.286,0],"ix":1,"l":2},"s":{"a":0,"k":[100,100,100],"ix":6,"l":2}},"ao":0,"w":1920,"h":1080,"ip":438.750827870687,"op":365.624024892171,"st":438.760817871094,"bm":0},{"ddd":0,"ind":2,"ty":0,"nm":"Pre-comp 2","refId":"comp_4","sr":1,"ks":{"o":{"a":0,"k":100,"ix":11},"r":{"a":1,"k":[{"i":{"x":[0.583],"y":[1]},"o":{"x":[0.024],"y":[1.043]},"t":292.507,"s":[90]},{"t":358.441214599609,"s":[0]}],"ix":10},"p":{"a":0,"k":[966,482.286,0],"ix":2,"l":2},"a":{"a":0,"k":[966,482.286,0],"ix":1,"l":2},"s":{"a":0,"k":[100,100,100],"ix":6,"l":2}},"ao":0,"w":1920,"h":1080,"ip":292.507211914063,"op":365.634014892578,"st":292.507211914063,"bm":0},{"ddd":0,"ind":3,"ty":0,"nm":"Pre-comp 2","refId":"comp_4","sr":-1,"ks":{"o":{"a":0,"k":100,"ix":11},"r":{"a":1,"k":[{"i":{"x":[0.583],"y":[1]},"o":{"x":[0.024],"y":[1.043]},"t":292.497,"s":[90]},{"t":226.563219228109,"s":[0]}],"ix":10},"p":{"a":0,"k":[966,482.286,0],"ix":2,"l":2},"a":{"a":0,"k":[966,482.286,0],"ix":1,"l":2},"s":{"a":0,"k":[100,100,100],"ix":6,"l":2}},"ao":0,"w":1920,"h":1080,"ip":292.497221913656,"op":219.37041893514,"st":292.507211914063,"bm":0},{"ddd":0,"ind":4,"ty":0,"nm":"Pre-comp 2","refId":"comp_4","sr":1,"ks":{"o":{"a":0,"k":100,"ix":11},"r":{"a":1,"k":[{"i":{"x":[0.583],"y":[1]},"o":{"x":[0.024],"y":[1.043]},"t":146.254,"s":[90]},{"t":212.187608642578,"s":[0]}],"ix":10},"p":{"a":0,"k":[966,482.286,0],"ix":2,"l":2},"a":{"a":0,"k":[966,482.286,0],"ix":1,"l":2},"s":{"a":0,"k":[100,100,100],"ix":6,"l":2}},"ao":0,"w":1920,"h":1080,"ip":146.253605957031,"op":219.380408935547,"st":146.253605957031,"bm":0},{"ddd":0,"ind":5,"ty":0,"nm":"Pre-comp 2","refId":"comp_4","sr":-1,"ks":{"o":{"a":0,"k":100,"ix":11},"r":{"a":1,"k":[{"i":{"x":[0.583],"y":[1]},"o":{"x":[0.024],"y":[1.043]},"t":146.244,"s":[90]},{"t":80.3096132710775,"s":[0]}],"ix":10},"p":{"a":0,"k":[966,482.286,0],"ix":2,"l":2},"a":{"a":0,"k":[966,482.286,0],"ix":1,"l":2},"s":{"a":0,"k":[100,100,100],"ix":6,"l":2}},"ao":0,"w":1920,"h":1080,"ip":146.243615956624,"op":73.1168129781087,"st":146.253605957031,"bm":0},{"ddd":0,"ind":6,"ty":0,"nm":"Pre-comp 2","refId":"comp_4","sr":1,"ks":{"o":{"a":0,"k":100,"ix":11},"r":{"a":1,"k":[{"i":{"x":[0.583],"y":[1]},"o":{"x":[0.024],"y":[1.043]},"t":0,"s":[90]},{"t":65.9340026855469,"s":[0]}],"ix":10},"p":{"a":0,"k":[966,482.286,0],"ix":2,"l":2},"a":{"a":0,"k":[966,482.286,0],"ix":1,"l":2},"s":{"a":0,"k":[100,100,100],"ix":6,"l":2}},"ao":0,"w":1920,"h":1080,"ip":0,"op":73.1268029785156,"st":0,"bm":0}]},{"id":"comp_4","nm":"Pre-comp 2","fr":25,"layers":[{"ddd":0,"ind":1,"ty":4,"nm":"Shape Layer 14","sr":1,"ks":{"o":{"a":0,"k":100,"ix":11},"r":{"a":0,"k":0,"ix":10},"p":{"s":true,"x":{"a":1,"k":[{"i":{"x":[0.342],"y":[1]},"o":{"x":[0.059],"y":[0.638]},"t":34.765,"s":[723.557]},{"t":59.9400024414062,"s":[975.446]}],"ix":3},"y":{"a":0,"k":481.143,"ix":4}},"a":{"a":0,"k":[0,-58.857,0],"ix":1,"l":2},"s":{"a":1,"k":[{"i":{"x":[0.833,0.833,0.833],"y":[1,1,1]},"o":{"x":[0.167,0.167,0.167],"y":[0,0,0]},"t":34.765,"s":[0,0,100]},{"t":59.9400024414062,"s":[-100,100,100]}],"ix":6,"l":2}},"ao":0,"shapes":[{"ty":"gr","it":[{"ind":0,"ty":"sh","ix":1,"ks":{"a":0,"k":{"i":[[0,0],[0,0],[0,0],[0,0],[0,0],[0,0]],"o":[[0,0],[0,0],[0,0],[0,0],[0,0],[0,0]],"v":[[104.667,-137.556],[97.778,-137.333],[27.778,-58.222],[97.778,20.889],[104.222,20.444],[35.556,-58.222]],"c":true},"ix":2},"nm":"Path 1","mn":"ADBE Vector Shape - Group","hd":false},{"ty":"fl","c":{"a":0,"k":[1,1,1,1],"ix":4},"o":{"a":0,"k":100,"ix":5},"r":1,"bm":0,"nm":"Fill 1","mn":"ADBE Vector Graphic - Fill","hd":false},{"ty":"tr","p":{"a":0,"k":[0,0],"ix":2},"a":{"a":0,"k":[0,0],"ix":1},"s":{"a":0,"k":[100,100],"ix":3},"r":{"a":0,"k":0,"ix":6},"o":{"a":0,"k":100,"ix":7},"sk":{"a":0,"k":0,"ix":4},"sa":{"a":0,"k":0,"ix":5},"nm":"Transform"}],"nm":"Shape 1","np":3,"cix":2,"bm":0,"ix":1,"mn":"ADBE Vector Group","hd":false}],"ip":34.7652014160156,"op":484.315219726563,"st":34.7652014160156,"bm":0},{"ddd":0,"ind":2,"ty":4,"nm":"Shape Layer 13","sr":1,"ks":{"o":{"a":0,"k":100,"ix":11},"r":{"a":0,"k":0,"ix":10},"p":{"s":true,"x":{"a":1,"k":[{"i":{"x":[0.342],"y":[1]},"o":{"x":[0.059],"y":[0.638]},"t":31.169,"s":[727.112]},{"t":56.3436022949219,"s":[979.001]}],"ix":3},"y":{"a":0,"k":481.143,"ix":4}},"a":{"a":0,"k":[0,-58.857,0],"ix":1,"l":2},"s":{"a":1,"k":[{"i":{"x":[0.833,0.833,0.833],"y":[1,1,1]},"o":{"x":[0.167,0.167,0.167],"y":[0,0,0]},"t":31.169,"s":[0,0,100]},{"t":56.3436022949219,"s":[-100,100,100]}],"ix":6,"l":2}},"ao":0,"shapes":[{"ty":"gr","it":[{"ind":0,"ty":"sh","ix":1,"ks":{"a":0,"k":{"i":[[0,0],[0,0],[0,0],[0,0],[0,0],[0,0]],"o":[[0,0],[0,0],[0,0],[0,0],[0,0],[0,0]],"v":[[104.667,-137.556],[97.778,-137.333],[27.778,-58.222],[97.778,20.889],[104.222,20.444],[35.556,-58.222]],"c":true},"ix":2},"nm":"Path 1","mn":"ADBE Vector Shape - Group","hd":false},{"ty":"fl","c":{"a":0,"k":[1,1,1,1],"ix":4},"o":{"a":0,"k":100,"ix":5},"r":1,"bm":0,"nm":"Fill 1","mn":"ADBE Vector Graphic - Fill","hd":false},{"ty":"tr","p":{"a":0,"k":[0,0],"ix":2},"a":{"a":0,"k":[0,0],"ix":1},"s":{"a":0,"k":[100,100],"ix":3},"r":{"a":0,"k":0,"ix":6},"o":{"a":0,"k":100,"ix":7},"sk":{"a":0,"k":0,"ix":4},"sa":{"a":0,"k":0,"ix":5},"nm":"Transform"}],"nm":"Shape 1","np":3,"cix":2,"bm":0,"ix":1,"mn":"ADBE Vector Group","hd":false}],"ip":31.1688012695313,"op":480.718819580078,"st":31.1688012695313,"bm":0},{"ddd":0,"ind":3,"ty":4,"nm":"Shape Layer 12","sr":1,"ks":{"o":{"a":0,"k":100,"ix":11},"r":{"a":0,"k":0,"ix":10},"p":{"s":true,"x":{"a":1,"k":[{"i":{"x":[0.342],"y":[1]},"o":{"x":[0.059],"y":[0.638]},"t":27.572,"s":[732.224]},{"t":52.7472021484375,"s":[984.112]}],"ix":3},"y":{"a":0,"k":481.143,"ix":4}},"a":{"a":0,"k":[0,-58.857,0],"ix":1,"l":2},"s":{"a":1,"k":[{"i":{"x":[0.833,0.833,0.833],"y":[1,1,1]},"o":{"x":[0.167,0.167,0.167],"y":[0,0,0]},"t":27.572,"s":[0,0,100]},{"t":52.7472021484375,"s":[-100,100,100]}],"ix":6,"l":2}},"ao":0,"shapes":[{"ty":"gr","it":[{"ind":0,"ty":"sh","ix":1,"ks":{"a":0,"k":{"i":[[0,0],[0,0],[0,0],[0,0],[0,0],[0,0]],"o":[[0,0],[0,0],[0,0],[0,0],[0,0],[0,0]],"v":[[104.667,-137.556],[97.778,-137.333],[27.778,-58.222],[97.778,20.889],[104.222,20.444],[35.556,-58.222]],"c":true},"ix":2},"nm":"Path 1","mn":"ADBE Vector Shape - Group","hd":false},{"ty":"fl","c":{"a":0,"k":[1,1,1,1],"ix":4},"o":{"a":0,"k":100,"ix":5},"r":1,"bm":0,"nm":"Fill 1","mn":"ADBE Vector Graphic - Fill","hd":false},{"ty":"tr","p":{"a":0,"k":[0,0],"ix":2},"a":{"a":0,"k":[0,0],"ix":1},"s":{"a":0,"k":[100,100],"ix":3},"r":{"a":0,"k":0,"ix":6},"o":{"a":0,"k":100,"ix":7},"sk":{"a":0,"k":0,"ix":4},"sa":{"a":0,"k":0,"ix":5},"nm":"Transform"}],"nm":"Shape 1","np":3,"cix":2,"bm":0,"ix":1,"mn":"ADBE Vector Group","hd":false}],"ip":27.5724011230469,"op":477.122419433594,"st":27.5724011230469,"bm":0},{"ddd":0,"ind":4,"ty":4,"nm":"Shape Layer 11","sr":1,"ks":{"o":{"a":0,"k":100,"ix":11},"r":{"a":0,"k":0,"ix":10},"p":{"s":true,"x":{"a":1,"k":[{"i":{"x":[0.342],"y":[1]},"o":{"x":[0.059],"y":[0.638]},"t":23.976,"s":[737.779]},{"t":49.1508020019531,"s":[989.668]}],"ix":3},"y":{"a":0,"k":481.143,"ix":4}},"a":{"a":0,"k":[0,-58.857,0],"ix":1,"l":2},"s":{"a":1,"k":[{"i":{"x":[0.833,0.833,0.833],"y":[1,1,1]},"o":{"x":[0.167,0.167,0.167],"y":[0,0,0]},"t":23.976,"s":[0,0,100]},{"t":49.1508020019531,"s":[-100,100,100]}],"ix":6,"l":2}},"ao":0,"shapes":[{"ty":"gr","it":[{"ind":0,"ty":"sh","ix":1,"ks":{"a":0,"k":{"i":[[0,0],[0,0],[0,0],[0,0],[0,0],[0,0]],"o":[[0,0],[0,0],[0,0],[0,0],[0,0],[0,0]],"v":[[104.667,-137.556],[97.778,-137.333],[27.778,-58.222],[97.778,20.889],[104.222,20.444],[35.556,-58.222]],"c":true},"ix":2},"nm":"Path 1","mn":"ADBE Vector Shape - Group","hd":false},{"ty":"fl","c":{"a":0,"k":[1,1,1,1],"ix":4},"o":{"a":0,"k":100,"ix":5},"r":1,"bm":0,"nm":"Fill 1","mn":"ADBE Vector Graphic - Fill","hd":false},{"ty":"tr","p":{"a":0,"k":[0,0],"ix":2},"a":{"a":0,"k":[0,0],"ix":1},"s":{"a":0,"k":[100,100],"ix":3},"r":{"a":0,"k":0,"ix":6},"o":{"a":0,"k":100,"ix":7},"sk":{"a":0,"k":0,"ix":4},"sa":{"a":0,"k":0,"ix":5},"nm":"Transform"}],"nm":"Shape 1","np":3,"cix":2,"bm":0,"ix":1,"mn":"ADBE Vector Group","hd":false}],"ip":23.9760009765625,"op":473.526019287109,"st":23.9760009765625,"bm":0},{"ddd":0,"ind":5,"ty":4,"nm":"Shape Layer 10","sr":1,"ks":{"o":{"a":0,"k":100,"ix":11},"r":{"a":0,"k":0,"ix":10},"p":{"s":true,"x":{"a":1,"k":[{"i":{"x":[0.342],"y":[1]},"o":{"x":[0.059],"y":[0.638]},"t":17.982,"s":[743.779]},{"t":43.1568017578125,"s":[995.668]}],"ix":3},"y":{"a":0,"k":481.143,"ix":4}},"a":{"a":0,"k":[0,-58.857,0],"ix":1,"l":2},"s":{"a":1,"k":[{"i":{"x":[0.833,0.833,0.833],"y":[1,1,1]},"o":{"x":[0.167,0.167,0.167],"y":[0,0,0]},"t":17.982,"s":[0,0,100]},{"t":43.1568017578125,"s":[-100,100,100]}],"ix":6,"l":2}},"ao":0,"shapes":[{"ty":"gr","it":[{"ind":0,"ty":"sh","ix":1,"ks":{"a":0,"k":{"i":[[0,0],[0,0],[0,0],[0,0],[0,0],[0,0]],"o":[[0,0],[0,0],[0,0],[0,0],[0,0],[0,0]],"v":[[104.667,-137.556],[97.778,-137.333],[27.778,-58.222],[97.778,20.889],[104.222,20.444],[35.556,-58.222]],"c":true},"ix":2},"nm":"Path 1","mn":"ADBE Vector Shape - Group","hd":false},{"ty":"fl","c":{"a":0,"k":[1,1,1,1],"ix":4},"o":{"a":0,"k":100,"ix":5},"r":1,"bm":0,"nm":"Fill 1","mn":"ADBE Vector Graphic - Fill","hd":false},{"ty":"tr","p":{"a":0,"k":[0,0],"ix":2},"a":{"a":0,"k":[0,0],"ix":1},"s":{"a":0,"k":[100,100],"ix":3},"r":{"a":0,"k":0,"ix":6},"o":{"a":0,"k":100,"ix":7},"sk":{"a":0,"k":0,"ix":4},"sa":{"a":0,"k":0,"ix":5},"nm":"Transform"}],"nm":"Shape 1","np":3,"cix":2,"bm":0,"ix":1,"mn":"ADBE Vector Group","hd":false}],"ip":17.9820007324219,"op":467.532019042969,"st":17.9820007324219,"bm":0},{"ddd":0,"ind":6,"ty":4,"nm":"Shape Layer 9","sr":1,"ks":{"o":{"a":0,"k":100,"ix":11},"r":{"a":0,"k":0,"ix":10},"p":{"s":true,"x":{"a":1,"k":[{"i":{"x":[0.342],"y":[1]},"o":{"x":[0.059],"y":[0.638]},"t":13.187,"s":[750.001]},{"t":38.3616015625,"s":[1001.89]}],"ix":3},"y":{"a":0,"k":481.143,"ix":4}},"a":{"a":0,"k":[0,-58.857,0],"ix":1,"l":2},"s":{"a":1,"k":[{"i":{"x":[0.833,0.833,0.833],"y":[1,1,1]},"o":{"x":[0.167,0.167,0.167],"y":[0,0,0]},"t":13.187,"s":[0,0,100]},{"t":38.3616015625,"s":[-100,100,100]}],"ix":6,"l":2}},"ao":0,"shapes":[{"ty":"gr","it":[{"ind":0,"ty":"sh","ix":1,"ks":{"a":0,"k":{"i":[[0,0],[0,0],[0,0],[0,0],[0,0],[0,0]],"o":[[0,0],[0,0],[0,0],[0,0],[0,0],[0,0]],"v":[[104.667,-137.556],[97.778,-137.333],[27.778,-58.222],[97.778,20.889],[104.222,20.444],[35.556,-58.222]],"c":true},"ix":2},"nm":"Path 1","mn":"ADBE Vector Shape - Group","hd":false},{"ty":"fl","c":{"a":0,"k":[1,1,1,1],"ix":4},"o":{"a":0,"k":100,"ix":5},"r":1,"bm":0,"nm":"Fill 1","mn":"ADBE Vector Graphic - Fill","hd":false},{"ty":"tr","p":{"a":0,"k":[0,0],"ix":2},"a":{"a":0,"k":[0,0],"ix":1},"s":{"a":0,"k":[100,100],"ix":3},"r":{"a":0,"k":0,"ix":6},"o":{"a":0,"k":100,"ix":7},"sk":{"a":0,"k":0,"ix":4},"sa":{"a":0,"k":0,"ix":5},"nm":"Transform"}],"nm":"Shape 1","np":3,"cix":2,"bm":0,"ix":1,"mn":"ADBE Vector Group","hd":false}],"ip":13.1868005371094,"op":462.736818847656,"st":13.1868005371094,"bm":0},{"ddd":0,"ind":7,"ty":4,"nm":"Shape Layer 8","sr":1,"ks":{"o":{"a":0,"k":100,"ix":11},"r":{"a":0,"k":0,"ix":10},"p":{"s":true,"x":{"a":1,"k":[{"i":{"x":[0.342],"y":[1]},"o":{"x":[0.059],"y":[0.638]},"t":8.392,"s":[756.001]},{"t":33.5664013671875,"s":[1007.89]}],"ix":3},"y":{"a":0,"k":481.143,"ix":4}},"a":{"a":0,"k":[0,-58.857,0],"ix":1,"l":2},"s":{"a":1,"k":[{"i":{"x":[0.833,0.833,0.833],"y":[1,1,1]},"o":{"x":[0.167,0.167,0.167],"y":[0,0,0]},"t":8.392,"s":[0,0,100]},{"t":33.5664013671875,"s":[-100,100,100]}],"ix":6,"l":2}},"ao":0,"shapes":[{"ty":"gr","it":[{"ind":0,"ty":"sh","ix":1,"ks":{"a":0,"k":{"i":[[0,0],[0,0],[0,0],[0,0],[0,0],[0,0]],"o":[[0,0],[0,0],[0,0],[0,0],[0,0],[0,0]],"v":[[104.667,-137.556],[97.778,-137.333],[27.778,-58.222],[97.778,20.889],[104.222,20.444],[35.556,-58.222]],"c":true},"ix":2},"nm":"Path 1","mn":"ADBE Vector Shape - Group","hd":false},{"ty":"fl","c":{"a":0,"k":[1,1,1,1],"ix":4},"o":{"a":0,"k":100,"ix":5},"r":1,"bm":0,"nm":"Fill 1","mn":"ADBE Vector Graphic - Fill","hd":false},{"ty":"tr","p":{"a":0,"k":[0,0],"ix":2},"a":{"a":0,"k":[0,0],"ix":1},"s":{"a":0,"k":[100,100],"ix":3},"r":{"a":0,"k":0,"ix":6},"o":{"a":0,"k":100,"ix":7},"sk":{"a":0,"k":0,"ix":4},"sa":{"a":0,"k":0,"ix":5},"nm":"Transform"}],"nm":"Shape 1","np":3,"cix":2,"bm":0,"ix":1,"mn":"ADBE Vector Group","hd":false}],"ip":8.39160034179688,"op":457.941618652344,"st":8.39160034179688,"bm":0},{"ddd":0,"ind":8,"ty":4,"nm":"Shape Layer 7","sr":1,"ks":{"o":{"a":0,"k":100,"ix":11},"r":{"a":0,"k":0,"ix":10},"p":{"s":true,"x":{"a":1,"k":[{"i":{"x":[0.342],"y":[1]},"o":{"x":[0.059],"y":[0.638]},"t":4.795,"s":[762.224]},{"t":29.9700012207031,"s":[1014.113]}],"ix":3},"y":{"a":0,"k":481.143,"ix":4}},"a":{"a":0,"k":[0,-58.857,0],"ix":1,"l":2},"s":{"a":1,"k":[{"i":{"x":[0.833,0.833,0.833],"y":[1,1,1]},"o":{"x":[0.167,0.167,0.167],"y":[0,0,0]},"t":4.795,"s":[0,0,100]},{"t":29.9700012207031,"s":[-100,100,100]}],"ix":6,"l":2}},"ao":0,"shapes":[{"ty":"gr","it":[{"ind":0,"ty":"sh","ix":1,"ks":{"a":0,"k":{"i":[[0,0],[0,0],[0,0],[0,0],[0,0],[0,0]],"o":[[0,0],[0,0],[0,0],[0,0],[0,0],[0,0]],"v":[[104.667,-137.556],[97.778,-137.333],[27.778,-58.222],[97.778,20.889],[104.222,20.444],[35.556,-58.222]],"c":true},"ix":2},"nm":"Path 1","mn":"ADBE Vector Shape - Group","hd":false},{"ty":"fl","c":{"a":0,"k":[1,1,1,1],"ix":4},"o":{"a":0,"k":100,"ix":5},"r":1,"bm":0,"nm":"Fill 1","mn":"ADBE Vector Graphic - Fill","hd":false},{"ty":"tr","p":{"a":0,"k":[0,0],"ix":2},"a":{"a":0,"k":[0,0],"ix":1},"s":{"a":0,"k":[100,100],"ix":3},"r":{"a":0,"k":0,"ix":6},"o":{"a":0,"k":100,"ix":7},"sk":{"a":0,"k":0,"ix":4},"sa":{"a":0,"k":0,"ix":5},"nm":"Transform"}],"nm":"Shape 1","np":3,"cix":2,"bm":0,"ix":1,"mn":"ADBE Vector Group","hd":false}],"ip":4.7952001953125,"op":454.345218505859,"st":4.7952001953125,"bm":0},{"ddd":0,"ind":9,"ty":4,"nm":"Shape Layer 6","sr":1,"ks":{"o":{"a":0,"k":100,"ix":11},"r":{"a":0,"k":0,"ix":10},"p":{"s":true,"x":{"a":1,"k":[{"i":{"x":[0.342],"y":[1]},"o":{"x":[0.059],"y":[0.638]},"t":0,"s":[768.224]},{"t":25.1748010253906,"s":[1020.113]}],"ix":3},"y":{"a":0,"k":481.143,"ix":4}},"a":{"a":0,"k":[0,-58.857,0],"ix":1,"l":2},"s":{"a":1,"k":[{"i":{"x":[0.833,0.833,0.833],"y":[1,1,1]},"o":{"x":[0.167,0.167,0.167],"y":[0,0,0]},"t":0,"s":[0,0,100]},{"t":25.1748010253906,"s":[-100,100,100]}],"ix":6,"l":2}},"ao":0,"shapes":[{"ty":"gr","it":[{"ind":0,"ty":"sh","ix":1,"ks":{"a":0,"k":{"i":[[0,0],[0,0],[0,0],[0,0],[0,0],[0,0]],"o":[[0,0],[0,0],[0,0],[0,0],[0,0],[0,0]],"v":[[104.667,-137.556],[97.778,-137.333],[27.778,-58.222],[97.778,20.889],[104.222,20.444],[35.556,-58.222]],"c":true},"ix":2},"nm":"Path 1","mn":"ADBE Vector Shape - Group","hd":false},{"ty":"fl","c":{"a":0,"k":[1,1,1,1],"ix":4},"o":{"a":0,"k":100,"ix":5},"r":1,"bm":0,"nm":"Fill 1","mn":"ADBE Vector Graphic - Fill","hd":false},{"ty":"tr","p":{"a":0,"k":[0,0],"ix":2},"a":{"a":0,"k":[0,0],"ix":1},"s":{"a":0,"k":[100,100],"ix":3},"r":{"a":0,"k":0,"ix":6},"o":{"a":0,"k":100,"ix":7},"sk":{"a":0,"k":0,"ix":4},"sa":{"a":0,"k":0,"ix":5},"nm":"Transform"}],"nm":"Shape 1","np":3,"cix":2,"bm":0,"ix":1,"mn":"ADBE Vector Group","hd":false}],"ip":0,"op":449.550018310547,"st":0,"bm":0},{"ddd":0,"ind":10,"ty":4,"nm":"Shape Layer 5","sr":1,"ks":{"o":{"a":0,"k":100,"ix":11},"r":{"a":0,"k":0,"ix":10},"p":{"s":true,"x":{"a":1,"k":[{"i":{"x":[0.342],"y":[1]},"o":{"x":[0.059],"y":[1.123]},"t":14.386,"s":[768.224]},{"t":39.5604016113281,"s":[911.224]}],"ix":3},"y":{"a":0,"k":481.143,"ix":4}},"a":{"a":0,"k":[0,-58.857,0],"ix":1,"l":2},"s":{"a":1,"k":[{"i":{"x":[0.667,0.667,0.667],"y":[1,1,1]},"o":{"x":[0.333,0.333,0.333],"y":[0,0,0]},"t":14.386,"s":[0,0,100]},{"t":39.5604016113281,"s":[100,100,100]}],"ix":6,"l":2}},"ao":0,"shapes":[{"ty":"gr","it":[{"ind":0,"ty":"sh","ix":1,"ks":{"a":0,"k":{"i":[[0,0],[0,0],[0,0],[0,0],[0,0],[0,0]],"o":[[0,0],[0,0],[0,0],[0,0],[0,0],[0,0]],"v":[[104.667,-137.556],[97.778,-137.333],[27.778,-58.222],[97.778,20.889],[104.222,20.444],[35.556,-58.222]],"c":true},"ix":2},"nm":"Path 1","mn":"ADBE Vector Shape - Group","hd":false},{"ty":"fl","c":{"a":0,"k":[1,1,1,1],"ix":4},"o":{"a":0,"k":100,"ix":5},"r":1,"bm":0,"nm":"Fill 1","mn":"ADBE Vector Graphic - Fill","hd":false},{"ty":"tr","p":{"a":0,"k":[0,0],"ix":2},"a":{"a":0,"k":[0,0],"ix":1},"s":{"a":0,"k":[100,100],"ix":3},"r":{"a":0,"k":0,"ix":6},"o":{"a":0,"k":100,"ix":7},"sk":{"a":0,"k":0,"ix":4},"sa":{"a":0,"k":0,"ix":5},"nm":"Transform"}],"nm":"Shape 1","np":3,"cix":2,"bm":0,"ix":1,"mn":"ADBE Vector Group","hd":false}],"ip":14.3856005859375,"op":463.935618896484,"st":14.3856005859375,"bm":0},{"ddd":0,"ind":11,"ty":4,"nm":"Shape Layer 4","sr":1,"ks":{"o":{"a":0,"k":100,"ix":11},"r":{"a":0,"k":0,"ix":10},"p":{"s":true,"x":{"a":1,"k":[{"i":{"x":[0.342],"y":[1]},"o":{"x":[0.059],"y":[1.123]},"t":9.59,"s":[779.812]},{"t":34.7652014160156,"s":[922.812]}],"ix":3},"y":{"a":0,"k":481.143,"ix":4}},"a":{"a":0,"k":[0,-58.857,0],"ix":1,"l":2},"s":{"a":1,"k":[{"i":{"x":[0.667,0.667,0.667],"y":[1,1,1]},"o":{"x":[0.333,0.333,0.333],"y":[0,0,0]},"t":9.59,"s":[0,0,100]},{"t":34.7652014160156,"s":[100,100,100]}],"ix":6,"l":2}},"ao":0,"shapes":[{"ty":"gr","it":[{"ind":0,"ty":"sh","ix":1,"ks":{"a":0,"k":{"i":[[0,0],[0,0],[0,0],[0,0],[0,0],[0,0]],"o":[[0,0],[0,0],[0,0],[0,0],[0,0],[0,0]],"v":[[104.667,-137.556],[97.778,-137.333],[27.778,-58.222],[97.778,20.889],[104.222,20.444],[35.556,-58.222]],"c":true},"ix":2},"nm":"Path 1","mn":"ADBE Vector Shape - Group","hd":false},{"ty":"fl","c":{"a":0,"k":[1,1,1,1],"ix":4},"o":{"a":0,"k":100,"ix":5},"r":1,"bm":0,"nm":"Fill 1","mn":"ADBE Vector Graphic - Fill","hd":false},{"ty":"tr","p":{"a":0,"k":[0,0],"ix":2},"a":{"a":0,"k":[0,0],"ix":1},"s":{"a":0,"k":[100,100],"ix":3},"r":{"a":0,"k":0,"ix":6},"o":{"a":0,"k":100,"ix":7},"sk":{"a":0,"k":0,"ix":4},"sa":{"a":0,"k":0,"ix":5},"nm":"Transform"}],"nm":"Shape 1","np":3,"cix":2,"bm":0,"ix":1,"mn":"ADBE Vector Group","hd":false}],"ip":9.590400390625,"op":459.140418701172,"st":9.590400390625,"bm":0},{"ddd":0,"ind":12,"ty":4,"nm":"Shape Layer 3","sr":1,"ks":{"o":{"a":0,"k":100,"ix":11},"r":{"a":0,"k":0,"ix":10},"p":{"s":true,"x":{"a":1,"k":[{"i":{"x":[0.342],"y":[1]},"o":{"x":[0.059],"y":[1.123]},"t":5.994,"s":[792.103]},{"t":31.1688012695313,"s":[935.103]}],"ix":3},"y":{"a":0,"k":481.143,"ix":4}},"a":{"a":0,"k":[0,-58.857,0],"ix":1,"l":2},"s":{"a":1,"k":[{"i":{"x":[0.667,0.667,0.667],"y":[1,1,1]},"o":{"x":[0.333,0.333,0.333],"y":[0,0,0]},"t":5.994,"s":[0,0,100]},{"t":31.1688012695313,"s":[100,100,100]}],"ix":6,"l":2}},"ao":0,"shapes":[{"ty":"gr","it":[{"ind":0,"ty":"sh","ix":1,"ks":{"a":0,"k":{"i":[[0,0],[0,0],[0,0],[0,0],[0,0],[0,0]],"o":[[0,0],[0,0],[0,0],[0,0],[0,0],[0,0]],"v":[[104.667,-137.556],[97.778,-137.333],[27.778,-58.222],[97.778,20.889],[104.222,20.444],[35.556,-58.222]],"c":true},"ix":2},"nm":"Path 1","mn":"ADBE Vector Shape - Group","hd":false},{"ty":"fl","c":{"a":0,"k":[1,1,1,1],"ix":4},"o":{"a":0,"k":100,"ix":5},"r":1,"bm":0,"nm":"Fill 1","mn":"ADBE Vector Graphic - Fill","hd":false},{"ty":"tr","p":{"a":0,"k":[0,0],"ix":2},"a":{"a":0,"k":[0,0],"ix":1},"s":{"a":0,"k":[100,100],"ix":3},"r":{"a":0,"k":0,"ix":6},"o":{"a":0,"k":100,"ix":7},"sk":{"a":0,"k":0,"ix":4},"sa":{"a":0,"k":0,"ix":5},"nm":"Transform"}],"nm":"Shape 1","np":3,"cix":2,"bm":0,"ix":1,"mn":"ADBE Vector Group","hd":false}],"ip":5.99400024414063,"op":455.544018554687,"st":5.99400024414063,"bm":0},{"ddd":0,"ind":13,"ty":4,"nm":"Shape Layer 2","sr":1,"ks":{"o":{"a":0,"k":100,"ix":11},"r":{"a":0,"k":0,"ix":10},"p":{"s":true,"x":{"a":1,"k":[{"i":{"x":[0.342],"y":[1]},"o":{"x":[0.059],"y":[1.123]},"t":2.398,"s":[804.709]},{"t":27.5724011230469,"s":[947.709]}],"ix":3},"y":{"a":0,"k":481.143,"ix":4}},"a":{"a":0,"k":[0,-58.857,0],"ix":1,"l":2},"s":{"a":1,"k":[{"i":{"x":[0.667,0.667,0.667],"y":[1,1,1]},"o":{"x":[0.333,0.333,0.333],"y":[0,0,0]},"t":2.398,"s":[0,0,100]},{"t":27.5724011230469,"s":[100,100,100]}],"ix":6,"l":2}},"ao":0,"shapes":[{"ty":"gr","it":[{"ind":0,"ty":"sh","ix":1,"ks":{"a":0,"k":{"i":[[0,0],[0,0],[0,0],[0,0],[0,0],[0,0]],"o":[[0,0],[0,0],[0,0],[0,0],[0,0],[0,0]],"v":[[104.667,-137.556],[97.778,-137.333],[27.778,-58.222],[97.778,20.889],[104.222,20.444],[35.556,-58.222]],"c":true},"ix":2},"nm":"Path 1","mn":"ADBE Vector Shape - Group","hd":false},{"ty":"fl","c":{"a":0,"k":[1,1,1,1],"ix":4},"o":{"a":0,"k":100,"ix":5},"r":1,"bm":0,"nm":"Fill 1","mn":"ADBE Vector Graphic - Fill","hd":false},{"ty":"tr","p":{"a":0,"k":[0,0],"ix":2},"a":{"a":0,"k":[0,0],"ix":1},"s":{"a":0,"k":[100,100],"ix":3},"r":{"a":0,"k":0,"ix":6},"o":{"a":0,"k":100,"ix":7},"sk":{"a":0,"k":0,"ix":4},"sa":{"a":0,"k":0,"ix":5},"nm":"Transform"}],"nm":"Shape 1","np":3,"cix":2,"bm":0,"ix":1,"mn":"ADBE Vector Group","hd":false}],"ip":2.39760009765625,"op":451.947618408203,"st":2.39760009765625,"bm":0},{"ddd":0,"ind":14,"ty":4,"nm":"Shape Layer 1","sr":1,"ks":{"o":{"a":0,"k":100,"ix":11},"r":{"a":0,"k":0,"ix":10},"p":{"s":true,"x":{"a":1,"k":[{"i":{"x":[0.342],"y":[1]},"o":{"x":[0.059],"y":[1.123]},"t":0,"s":[817]},{"t":25.1748010253906,"s":[960]}],"ix":3},"y":{"a":0,"k":481.143,"ix":4}},"a":{"a":0,"k":[0,-58.857,0],"ix":1,"l":2},"s":{"a":1,"k":[{"i":{"x":[0.667,0.667,0.667],"y":[1,1,1]},"o":{"x":[0.333,0.333,0.333],"y":[0,0,0]},"t":0,"s":[0,0,100]},{"t":25.1748010253906,"s":[100,100,100]}],"ix":6,"l":2}},"ao":0,"shapes":[{"ty":"gr","it":[{"ind":0,"ty":"sh","ix":1,"ks":{"a":0,"k":{"i":[[0,0],[0,0],[0,0],[0,0],[0,0],[0,0]],"o":[[0,0],[0,0],[0,0],[0,0],[0,0],[0,0]],"v":[[104.667,-137.556],[97.778,-137.333],[27.778,-58.222],[97.778,20.889],[104.222,20.444],[35.556,-58.222]],"c":true},"ix":2},"nm":"Path 1","mn":"ADBE Vector Shape - Group","hd":false},{"ty":"fl","c":{"a":0,"k":[1,1,1,1],"ix":4},"o":{"a":0,"k":100,"ix":5},"r":1,"bm":0,"nm":"Fill 1","mn":"ADBE Vector Graphic - Fill","hd":false},{"ty":"tr","p":{"a":0,"k":[0,0],"ix":2},"a":{"a":0,"k":[0,0],"ix":1},"s":{"a":0,"k":[100,100],"ix":3},"r":{"a":0,"k":0,"ix":6},"o":{"a":0,"k":100,"ix":7},"sk":{"a":0,"k":0,"ix":4},"sa":{"a":0,"k":0,"ix":5},"nm":"Transform"}],"nm":"Shape 1","np":3,"cix":2,"bm":0,"ix":1,"mn":"ADBE Vector Group","hd":false}],"ip":0,"op":449.550018310547,"st":0,"bm":0}]}],"fonts":{"list":[{"fName":"FuturaPT-Book","fFamily":"Futura PT","fStyle":"Book","ascent":72.8988647460938}]},"layers":[{"ddd":0,"ind":1,"ty":0,"nm":"Final_11","refId":"comp_0","sr":-1,"ks":{"o":{"a":0,"k":100,"ix":11},"r":{"a":0,"k":0,"ix":10},"p":{"a":0,"k":[146,162.556,0],"ix":2,"l":2},"a":{"a":0,"k":[960,540,0],"ix":1,"l":2},"s":{"a":0,"k":[100,100,100],"ix":6,"l":2}},"ao":0,"w":1920,"h":1080,"ip":218.990018919646,"op":153.990016272142,"st":219.000008920053,"bm":0},{"ddd":0,"ind":2,"ty":0,"nm":"Final_11","refId":"comp_0","sr":1,"ks":{"o":{"a":0,"k":100,"ix":11},"r":{"a":0,"k":0,"ix":10},"p":{"a":0,"k":[146,162.556,0],"ix":2,"l":2},"a":{"a":0,"k":[960,540,0],"ix":1,"l":2},"s":{"a":0,"k":[100,100,100],"ix":6,"l":2}},"ao":0,"w":1920,"h":1080,"ip":0,"op":135.000005498663,"st":0,"bm":0}],"markers":[{"tm":128.000005213547,"cm":"Move your time indicator here to change Logo_1 position","dr":0}],"chars":[{"ch":"l","size":65,"style":"Book","w":20.8,"data":{"shapes":[{"ty":"gr","it":[{"ind":0,"ty":"sh","ix":1,"ks":{"a":0,"k":{"i":[[0,0],[0,0],[0,0],[0,0]],"o":[[0,0],[0,0],[0,0],[0,0]],"v":[[6.848,-73.416],[6.848,0],[14.099,0],[14.099,-73.416]],"c":true},"ix":2},"nm":"l","mn":"ADBE Vector Shape - Group","hd":false}],"nm":"l","np":3,"cix":2,"bm":0,"ix":1,"mn":"ADBE Vector Group","hd":false}]},"fFamily":"Futura PT"},{"ch":"o","size":65,"style":"Book","w":52.4,"data":{"shapes":[{"ty":"gr","it":[{"ind":0,"ty":"sh","ix":1,"ks":{"a":0,"k":{"i":[[-12.689,0],[0,12.689],[12.79,0],[0,-12.689]],"o":[[12.689,0],[0,-12.689],[-12.79,0],[0,12.689]],"v":[[26.385,1.208],[48.541,-20.746],[26.385,-42.801],[4.23,-20.746]],"c":true},"ix":2},"nm":"o","mn":"ADBE Vector Shape - Group","hd":false},{"ind":1,"ty":"sh","ix":2,"ks":{"a":0,"k":{"i":[[-7.654,0],[0,-10.272],[7.553,0],[0,10.272]],"o":[[7.654,0],[0,10.172],[-7.452,0],[0,-10.172]],"v":[[26.385,-36.356],[41.089,-20.746],[26.385,-5.237],[11.682,-20.746]],"c":true},"ix":2},"nm":"o","mn":"ADBE Vector Shape - Group","hd":false}],"nm":"o","np":5,"cix":2,"bm":0,"ix":1,"mn":"ADBE Vector Group","hd":false}]},"fFamily":"Futura PT"},{"ch":"a","size":65,"style":"Book","w":52.6,"data":{"shapes":[{"ty":"gr","it":[{"ind":0,"ty":"sh","ix":1,"ks":{"a":0,"k":{"i":[[0,0],[8.057,0],[0,-14.401],[-10.574,0],[-2.417,3.122],[0,0],[0,0],[0,0],[0,0]],"o":[[-1.913,-2.518],[-10.675,0],[0,14.703],[7.352,0],[0,0],[0,0],[0,0],[0,0],[0,0]],"v":[[38.873,-35.852],[24.573,-42.801],[4.23,-20.947],[24.573,1.208],[38.873,-5.841],[38.873,0],[46.124,0],[46.124,-41.794],[38.873,-41.794]],"c":true},"ix":2},"nm":"a","mn":"ADBE Vector Shape - Group","hd":false},{"ind":1,"ty":"sh","ix":2,"ks":{"a":0,"k":{"i":[[-7.15,0],[0,-10.776],[8.862,0],[0,8.963]],"o":[[6.445,0],[0,8.258],[-8.661,0],[0,-10.172]],"v":[[25.378,-36.356],[39.276,-20.847],[25.378,-5.237],[11.682,-20.947]],"c":true},"ix":2},"nm":"a","mn":"ADBE Vector Shape - Group","hd":false}],"nm":"a","np":5,"cix":2,"bm":0,"ix":1,"mn":"ADBE Vector Group","hd":false}]},"fFamily":"Futura PT"},{"ch":"d","size":65,"style":"Book","w":52.6,"data":{"shapes":[{"ty":"gr","it":[{"ind":0,"ty":"sh","ix":1,"ks":{"a":0,"k":{"i":[[0,0],[8.057,0],[0,-14.401],[-10.574,0],[-2.417,3.122],[0,0],[0,0],[0,0],[0,0]],"o":[[-1.913,-2.518],[-10.675,0],[0,14.703],[7.352,0],[0,0],[0,0],[0,0],[0,0],[0,0]],"v":[[38.873,-35.852],[24.573,-42.801],[4.23,-20.947],[24.573,1.208],[38.873,-5.841],[38.873,0],[46.124,0],[46.124,-73.416],[38.873,-73.416]],"c":true},"ix":2},"nm":"d","mn":"ADBE Vector Shape - Group","hd":false},{"ind":1,"ty":"sh","ix":2,"ks":{"a":0,"k":{"i":[[-7.15,0],[0,-10.776],[8.862,0],[0,8.963]],"o":[[6.445,0],[0,8.258],[-8.661,0],[0,-10.172]],"v":[[25.378,-36.356],[39.276,-20.847],[25.378,-5.237],[11.682,-20.947]],"c":true},"ix":2},"nm":"d","mn":"ADBE Vector Shape - Group","hd":false}],"nm":"d","np":5,"cix":2,"bm":0,"ix":1,"mn":"ADBE Vector Group","hd":false}]},"fFamily":"Futura PT"},{"ch":"i","size":65,"style":"Book","w":20.8,"data":{"shapes":[{"ty":"gr","it":[{"ind":0,"ty":"sh","ix":1,"ks":{"a":0,"k":{"i":[[0,0],[0,0],[0,0],[0,0]],"o":[[0,0],[0,0],[0,0],[0,0]],"v":[[6.848,-41.794],[6.848,0],[14.099,0],[14.099,-41.794]],"c":true},"ix":2},"nm":"i","mn":"ADBE Vector Shape - Group","hd":false},{"ind":1,"ty":"sh","ix":2,"ks":{"a":0,"k":{"i":[[0,-2.82],[-2.82,0],[0,2.82],[2.82,0]],"o":[[0,2.82],[2.82,0],[0,-2.82],[-2.82,0]],"v":[[5.338,-57.605],[10.474,-52.469],[15.61,-57.605],[10.474,-62.741]],"c":true},"ix":2},"nm":"i","mn":"ADBE Vector Shape - Group","hd":false}],"nm":"i","np":5,"cix":2,"bm":0,"ix":1,"mn":"ADBE Vector Group","hd":false}]},"fFamily":"Futura PT"},{"ch":"n","size":65,"style":"Book","w":47,"data":{"shapes":[{"ty":"gr","it":[{"ind":0,"ty":"sh","ix":1,"ks":{"a":0,"k":{"i":[[0,0],[0,0],[0,0],[-2.82,3.323],[-2.518,0],[-1.41,-1.813],[0,-2.518],[0,0],[0,0],[0,0],[2.115,3.122],[4.935,0],[1.309,-1.712],[0,0],[0,0]],"o":[[0,0],[0,0],[0,-3.021],[2.115,-2.518],[3.223,0],[1.712,2.216],[0,0],[0,0],[0,0],[0,-4.633],[-2.518,-3.726],[-6.949,0],[0,0],[0,0],[0,0]],"v":[[6.848,0],[14.099,0],[14.099,-21.854],[17.12,-33.133],[24.472,-36.356],[31.32,-33.334],[33.234,-25.681],[33.234,0],[40.485,0],[40.485,-25.882],[38.068,-37.061],[26.083,-42.801],[14.099,-36.96],[14.099,-41.794],[6.848,-41.794]],"c":true},"ix":2},"nm":"n","mn":"ADBE Vector Shape - Group","hd":false}],"nm":"n","np":3,"cix":2,"bm":0,"ix":1,"mn":"ADBE Vector Group","hd":false}]},"fFamily":"Futura PT"},{"ch":"g","size":65,"style":"Book","w":52.6,"data":{"shapes":[{"ty":"gr","it":[{"ind":0,"ty":"sh","ix":1,"ks":{"a":0,"k":{"i":[[0,0],[6.143,0],[3.525,-3.424],[0,-8.157],[-2.82,-2.82],[-6.143,0],[-2.417,3.122],[0,0],[2.115,-3.424],[5.136,0],[3.021,3.323],[0,3.525],[0,0],[-2.82,-2.82],[-7.15,0],[-3.122,4.23],[0,4.532],[0,0],[0,0]],"o":[[-3.323,-4.33],[-5.64,0],[-3.021,3.021],[0,8.459],[3.223,3.223],[7.352,0],[0,0],[0,3.525],[-2.417,4.028],[-3.223,0],[-1.813,-2.014],[0,0],[0,6.143],[2.82,2.82],[7.855,0],[4.028,-5.438],[0,0],[0,0],[0,0]],"v":[[38.873,-35.852],[24.573,-42.801],[10.272,-37.161],[4.23,-20.947],[10.272,-4.431],[24.573,1.208],[38.873,-5.841],[38.873,0.201],[36.557,10.876],[25.479,16.718],[15.408,12.689],[12.186,4.028],[5.035,4.028],[10.474,17.523],[25.378,23.163],[42.096,15.408],[46.124,-1.007],[46.124,-41.794],[38.873,-41.794]],"c":true},"ix":2},"nm":"g","mn":"ADBE Vector Shape - Group","hd":false},{"ind":1,"ty":"sh","ix":2,"ks":{"a":0,"k":{"i":[[-4.431,0],[-2.316,-2.316],[0,-4.935],[2.82,-2.719],[3.827,0],[2.316,2.115],[0,3.625],[-3.525,3.625]],"o":[[3.726,0],[2.618,2.518],[0,4.935],[-2.316,2.316],[-3.827,0],[-4.028,-3.726],[0,-3.424],[2.014,-2.014]],"v":[[25.378,-36.356],[34.845,-32.629],[39.276,-20.847],[34.543,-8.762],[25.378,-5.237],[16.415,-8.661],[11.682,-20.947],[15.912,-32.428]],"c":true},"ix":2},"nm":"g","mn":"ADBE Vector Shape - Group","hd":false}],"nm":"g","np":5,"cix":2,"bm":0,"ix":1,"mn":"ADBE Vector Group","hd":false}]},"fFamily":"Futura PT"},{"ch":" ","size":65,"style":"Book","w":23.3,"data":{},"fFamily":"Futura PT"},{"ch":"L","size":65,"style":"Book","w":35.8,"data":{"shapes":[{"ty":"gr","it":[{"ind":0,"ty":"sh","ix":1,"ks":{"a":0,"k":{"i":[[0,0],[0,0],[0,0],[0,0],[0,0],[0,0]],"o":[[0,0],[0,0],[0,0],[0,0],[0,0],[0,0]],"v":[[8.661,-67.172],[8.661,0],[34.644,0],[34.644,-7.05],[16.113,-7.05],[16.113,-67.172]],"c":true},"ix":2},"nm":"L","mn":"ADBE Vector Shape - Group","hd":false}],"nm":"L","np":3,"cix":2,"bm":0,"ix":1,"mn":"ADBE Vector Group","hd":false}]},"fFamily":"Futura PT"},{"ch":"U","size":65,"style":"Book","w":64.6,"data":{"shapes":[{"ty":"gr","it":[{"ind":0,"ty":"sh","ix":1,"ks":{"a":0,"k":{"i":[[0,0],[0,0],[0,0],[-3.625,-5.035],[-8.56,0],[-4.028,5.539],[0,5.64],[0,0],[0,0],[0,0],[5.338,-4.532],[3.726,0],[2.719,2.316],[0,5.64]],"o":[[0,0],[0,0],[0,5.64],[4.028,5.539],[8.56,0],[3.625,-5.035],[0,0],[0,0],[0,0],[0,5.64],[-2.719,2.316],[-3.726,0],[-5.338,-4.532],[0,0]],"v":[[16.113,-67.172],[8.661,-67.172],[8.661,-23.969],[12.891,-7.855],[32.529,1.208],[52.167,-7.855],[56.396,-23.969],[56.396,-67.172],[48.944,-67.172],[48.944,-25.983],[43.607,-9.668],[32.529,-5.841],[21.451,-9.668],[16.113,-25.983]],"c":true},"ix":2},"nm":"U","mn":"ADBE Vector Shape - Group","hd":false}],"nm":"U","np":3,"cix":2,"bm":0,"ix":1,"mn":"ADBE Vector Group","hd":false}]},"fFamily":"Futura PT"},{"ch":"X","size":65,"style":"Book","w":50.4,"data":{"shapes":[{"ty":"gr","it":[{"ind":0,"ty":"sh","ix":1,"ks":{"a":0,"k":{"i":[[0,0],[0,0],[0,0],[0,0],[0,0],[0,0],[0,0],[0,0],[0,0],[0,0],[0,0],[0,0]],"o":[[0,0],[0,0],[0,0],[0,0],[0,0],[0,0],[0,0],[0,0],[0,0],[0,0],[0,0],[0,0]],"v":[[1.41,0],[9.869,0],[25.479,-27.594],[40.887,0],[49.347,0],[29.91,-34.744],[48.34,-67.172],[39.88,-67.172],[25.58,-41.895],[11.682,-67.172],[3.223,-67.172],[21.249,-34.744]],"c":true},"ix":2},"nm":"X","mn":"ADBE Vector Shape - Group","hd":false}],"nm":"X","np":3,"cix":2,"bm":0,"ix":1,"mn":"ADBE Vector Group","hd":false}]},"fFamily":"Futura PT"},{"ch":"v","size":65,"style":"Book","w":42.4,"data":{"shapes":[{"ty":"gr","it":[{"ind":0,"ty":"sh","ix":1,"ks":{"a":0,"k":{"i":[[0,0],[0,0],[0,0],[0,0],[0,0],[0,0]],"o":[[0,0],[0,0],[0,0],[0,0],[0,0],[0,0]],"v":[[0.806,-41.794],[21.35,2.719],[41.895,-41.794],[33.838,-41.794],[21.35,-13.596],[8.862,-41.794]],"c":true},"ix":2},"nm":"v","mn":"ADBE Vector Shape - Group","hd":false}],"nm":"v","np":3,"cix":2,"bm":0,"ix":1,"mn":"ADBE Vector Group","hd":false}]},"fFamily":"Futura PT"},{"ch":"s","size":65,"style":"Book","w":35.2,"data":{"shapes":[{"ty":"gr","it":[{"ind":0,"ty":"sh","ix":1,"ks":{"a":0,"k":{"i":[[0,0],[2.216,0],[0,-7.352],[-1.611,-2.014],[-5.035,-2.216],[0,-3.928],[4.733,0],[0.806,2.216],[0,0],[-1.712,0],[0,8.762],[1.813,2.216],[6.042,2.518],[0,3.021],[-2.618,0],[-1.007,-2.417]],"o":[[-3.323,-7.15],[-7.05,0],[0,2.115],[1.913,2.316],[3.928,1.712],[0,3.122],[-5.237,0],[0,0],[3.525,10.474],[8.057,0],[0,-2.316],[-1.611,-2.014],[-4.733,-2.014],[0,-3.223],[2.719,0],[0,0]],"v":[[30.011,-35.248],[18.53,-42.801],[6.345,-31.119],[8.258,-24.976],[18.43,-18.832],[25.177,-11.884],[18.329,-5.237],[9.869,-12.085],[3.625,-9.467],[18.228,1.208],[32.629,-12.488],[30.414,-19.235],[19.94,-25.681],[13.193,-31.622],[18.228,-36.356],[24.069,-32.126]],"c":true},"ix":2},"nm":"s","mn":"ADBE Vector Shape - Group","hd":false}],"nm":"s","np":3,"cix":2,"bm":0,"ix":1,"mn":"ADBE Vector Group","hd":false}]},"fFamily":"Futura PT"},{"ch":"u","size":65,"style":"Book","w":46.6,"data":{"shapes":[{"ty":"gr","it":[{"ind":0,"ty":"sh","ix":1,"ks":{"a":0,"k":{"i":[[0,0],[0,0],[0,0],[-3.323,-3.625],[-4.129,0],[-3.726,3.928],[0,5.136],[0,0],[0,0],[0,0],[2.014,-2.618],[4.028,0],[1.108,1.41],[0,2.921]],"o":[[0,0],[0,0],[0,5.136],[3.726,3.928],[4.129,0],[3.323,-3.625],[0,0],[0,0],[0,0],[0,2.921],[-1.108,1.41],[-4.028,0],[-2.014,-2.618],[0,0]],"v":[[14.099,-41.794],[6.848,-41.794],[6.848,-16.617],[10.675,-4.028],[23.465,1.208],[36.255,-4.028],[40.082,-16.617],[40.082,-41.794],[32.831,-41.794],[32.831,-17.422],[30.817,-8.459],[23.465,-5.237],[16.113,-8.459],[14.099,-17.422]],"c":true},"ix":2},"nm":"u","mn":"ADBE Vector Shape - Group","hd":false}],"nm":"u","np":3,"cix":2,"bm":0,"ix":1,"mn":"ADBE Vector Group","hd":false}]},"fFamily":"Futura PT"},{"ch":"z","size":65,"style":"Book","w":46,"data":{"shapes":[{"ty":"gr","it":[{"ind":0,"ty":"sh","ix":1,"ks":{"a":0,"k":{"i":[[0,0],[0,0],[0,0],[0,0],[0,0],[0,0],[0,0],[0,0]],"o":[[0,0],[0,0],[0,0],[0,0],[0,0],[0,0],[0,0],[0,0]],"v":[[45.52,-41.794],[6.647,-41.794],[6.647,-35.147],[31.018,-35.147],[0.806,0],[44.312,0],[44.312,-6.647],[15.308,-6.647]],"c":true},"ix":2},"nm":"z","mn":"ADBE Vector Shape - Group","hd":false}],"nm":"z","np":3,"cix":2,"bm":0,"ix":1,"mn":"ADBE Vector Group","hd":false}]},"fFamily":"Futura PT"},{"ch":"e","size":65,"style":"Book","w":48.1,"data":{"shapes":[{"ty":"gr","it":[{"ind":0,"ty":"sh","ix":1,"ks":{"a":0,"k":{"i":[[0,0],[1.913,-1.611],[3.424,0],[0.101,8.661],[0,0],[2.618,3.726],[8.157,0],[0,-12.488],[-10.071,0],[-3.827,3.424],[-1.208,2.316]],"o":[[-0.906,2.014],[-2.417,2.014],[-7.251,0],[0,0],[0.201,-5.539],[-2.518,-3.625],[-12.589,0],[0,15.509],[5.338,0],[2.115,-1.913],[0,0]],"v":[[37.866,-13.998],[33.536,-8.258],[24.976,-5.237],[11.682,-19.437],[44.211,-19.437],[40.283,-35.147],[24.472,-42.801],[4.23,-20.645],[24.875,1.208],[38.773,-3.928],[43.909,-10.675]],"c":true},"ix":2},"nm":"e","mn":"ADBE Vector Shape - Group","hd":false},{"ind":1,"ty":"sh","ix":2,"ks":{"a":0,"k":{"i":[[0,0],[-6.143,0],[-1.208,-6.546]],"o":[[1.108,-6.244],[6.143,0],[0,0]],"v":[[12.186,-25.479],[24.472,-36.356],[36.758,-25.479]],"c":true},"ix":2},"nm":"e","mn":"ADBE Vector Shape - Group","hd":false}],"nm":"e","np":5,"cix":2,"bm":0,"ix":1,"mn":"ADBE Vector Group","hd":false}]},"fFamily":"Futura PT"},{"ch":"r","size":65,"style":"Book","w":29.6,"data":{"shapes":[{"ty":"gr","it":[{"ind":0,"ty":"sh","ix":1,"ks":{"a":0,"k":{"i":[[0,0],[0,0],[0,0],[-1.208,1.611],[-2.921,0],[-1.611,-1.108],[0,0],[2.216,0],[0.705,-1.108],[0,0],[0,0]],"o":[[0,0],[0,0],[0,-6.848],[1.108,-1.41],[1.108,0],[0,0],[-1.813,-0.906],[-5.64,0],[0,0],[0,0],[0,0]],"v":[[6.848,0],[14.099,0],[14.099,-22.055],[16.516,-33.334],[22.357,-35.953],[26.587,-34.543],[30.011,-41.089],[23.566,-42.801],[14.099,-37.262],[14.099,-41.794],[6.848,-41.794]],"c":true},"ix":2},"nm":"r","mn":"ADBE Vector Shape - Group","hd":false}],"nm":"r","np":3,"cix":2,"bm":0,"ix":1,"mn":"ADBE Vector Group","hd":false}]},"fFamily":"Futura PT"},{"ch":".","size":65,"style":"Book","w":22.8,"data":{"shapes":[{"ty":"gr","it":[{"ind":0,"ty":"sh","ix":1,"ks":{"a":0,"k":{"i":[[0,-2.719],[-2.719,0],[0,2.719],[2.719,0]],"o":[[0,2.719],[2.719,0],[0,-2.719],[-2.719,0]],"v":[[6.445,-4.028],[11.481,1.007],[16.516,-4.028],[11.481,-9.064]],"c":true},"ix":2},"nm":".","mn":"ADBE Vector Shape - Group","hd":false}],"nm":".","np":3,"cix":2,"bm":0,"ix":1,"mn":"ADBE Vector Group","hd":false}]},"fFamily":"Futura PT"}]}